toolchain/top.v
// # -*- compile-command: "make all data.vcd" -*-
module top(/*AUTOARG*/
   // Outputs
   o_light_a, o_light_b,
   // Inputs
   i_clk, i_reset, i_test_a, i_test_b
   );


   input i_clk;
   input i_reset;
   
   input i_test_a;
   input i_test_b;
   
   output [1:0] o_light_a;
   output [1:0]   o_light_b;

   

   /*AUTOINPUT*/
   /*AUTOOUTPUT*/
   /*AUTOREG*/
   // Beginning of automatic regs (for this module's undeclared outputs)
   reg [1:0]            o_light_a;
   reg [1:0]            o_light_b;
   // End of automatics

   localparam state0 = 2'b00;
   localparam state1 = 2'b01;
   localparam state2 = 2'b10;
   localparam state3 = 2'b11;

   localparam green = 2'b00;
   localparam yellow = 2'b01;
   localparam red = 2'b10;
   localparam redyellow = 2'b11;
   
   reg [1:0]            state;
            
   always @(posedge i_clk) begin
       if (i_reset) begin
            /*AUTORESET*/
            // Beginning of autoreset for uninitialized flops
            o_light_a <= 2'h0;
            o_light_b <= 2'h0;
            state <= 2'h0;
            // End of automatics

          state <= state1;
          o_light_a <= green;
          o_light_b <= red;

       end // if (!i_reset)

      case(state)
        state0:
             if (~i_test_a) begin
                state<=state1;
                o_light_a <=  yellow;
                o_light_b <= redyellow;
             end
        state1:
          begin
             state<=state2;
             o_light_a <= red;
             o_light_b <= green;
          end
        state2:
          begin
             if (~i_test_b) begin
                state<=state3;
                o_light_a <= redyellow;
                o_light_b <= yellow;
             end
          end
        state3:
          begin
             state<=state0;
             o_light_a <= green;
             o_light_b <= red;
             end
        endcase
   end
endmodule

toolchain/data.vcd
$version Generated by VerilatedVcd $end
$date Mon Mar 11 12:22:48 2019
 $end
$timescale   1ns $end

 $scope module TOP $end
  $var wire  1 $ i_clk $end
  $var wire  1 % i_reset $end
  $var wire  1 & i_test_a $end
  $var wire  1 ' i_test_b $end
  $var wire  2 ( o_light_a [1:0] $end
  $var wire  2 ) o_light_b [1:0] $end
  $scope module top $end
   $var wire  2 * green [1:0] $end
   $var wire  1 $ i_clk $end
   $var wire  1 % i_reset $end
   $var wire  1 & i_test_a $end
   $var wire  1 ' i_test_b $end
   $var wire  2 ( o_light_a [1:0] $end
   $var wire  2 ) o_light_b [1:0] $end
   $var wire  2 , red [1:0] $end
   $var wire  2 - redyellow [1:0] $end
   $var wire  2 # state [1:0] $end
   $var wire  2 * state0 [1:0] $end
   $var wire  2 + state1 [1:0] $end
   $var wire  2 , state2 [1:0] $end
   $var wire  2 - state3 [1:0] $end
   $var wire  2 + yellow [1:0] $end
  $upscope $end
 $upscope $end
$enddefinitions $end


#0
b00 #
0$
1%
0&
0'
b00 (
b00 )
b00 *
b01 +
b10 ,
b11 -
#1
b01 #
1$
1&
1'
b10 )
#2
0$
0&
0'
#3
1$
1&
#4
0$
0&
1'
#5
1$
0%
1&
0'
#6
0$
0&
#7
b10 #
1$
1'
b10 (
b00 )
#8
0$
1&
0'
#9
1$
0&
#10
0$
1&
1'
#11
1$
0&
0'
#12
0$
1&
#13
1$
0&
1'
#14
0$
0'
#15
b11 #
1$
1&
b11 (
b01 )
#16
0$
0&
1'
#17
1$
1&
0'
#18
0$
0&
#19
1$
1&
1'
#20
0$
0&
0'
#21
b00 #
1$
b00 (
b10 )
#22
0$
1&
1'
#23
1$
0&
0'
#24
0$
1&
#25
1$
0&
1'
#26
0$
1&
0'
#27
1$
0&
#28
0$
1'
#29
1$
1&
0'
#30
0$
0&
#31
1$
1&
1'
#32
0$
0&
0'
#33
1$
1&
#34
0$
0&
1'
#35
1$
0'
#36
0$
1&
#37
1$
0&
1'
#38
0$
1&
0'
#39
1$
0&
#40
0$
1&
1'
#41
1$
0&
0'
#42
0$
#43
1$
1&
1'
#44
0$
0&
0'
#45
1$
1&
#46
0$
0&
1'
#47
1$
1&
0'
#48
0$
0&
#49
b01 #
1$
1'
b01 (
b11 )
#50
0$
1&
0'
#51
1$
0&
#52
0$
1&
1'
#53
1$
0&
0'
#54
0$
1&
#55
1$
0&
1'
#56
0$
0'
#57
b10 #
1$
1&
b10 (
b00 )
#58
0$
0&
1'
#59
1$
1&
0'
#60
0$
0&
#61
1$
1&
1'
#62
0$
0&
0'
#63
b11 #
1$
b11 (
b01 )
#64
0$
1&
1'
#65
1$
0&
0'
#66
0$
1&
#67
1$
0&
1'
#68
0$
1&
0'
#69
1$
0&
#70
0$
1'
#71
b00 #
1$
1&
0'
b00 (
b10 )
#72
0$
0&
#73
1$
1&
1'
#74
0$
0&
0'
#75
1$
1&
#76
0$
0&
1'
#77
1$
0'
#78
0$
1&
#79
1$
0&
1'
#80
0$
1&
0'
#81
1$
0&
#82
0$
1&
1'
#83
1$
0&
0'
#84
0$
#85
1$
1&
1'
#86
0$
0&
0'
#87
1$
1&
#88
0$
0&
1'
#89
1$
1&
0'
#90
0$
0&
#91
b01 #
1$
1'
b01 (
b11 )
#92
0$
1&
0'
#93
1$
0&
#94
0$
1&
1'
#95
1$
0&
0'
#96
0$
1&
#97
1$
0&
1'
#98
0$
0'
#99
b10 #
1$
1&
b10 (
b00 )
#100
0$
0&
1'
#101
1$
1&
0'
#102
0$
0&
#103
1$
1&
1'
#104
0$
0&
0'
#105
b11 #
1$
b11 (
b01 )
#106
0$
1&
1'
#107
1$
0&
0'
#108
0$
1&
#109
1$
0&
1'
#110
0$
1&
0'
#111
1$
0&
#112
0$
1'
#113
b00 #
1$
1&
0'
b00 (
b10 )
#114
0$
0&
#115
1$
1&
1'
#116
0$
0&
0'
#117
1$
1&
#118
0$
0&
1'
#119
1$
0'
#120
0$
1&
#121
1$
0&
1'
#122
0$
1&
0'
#123
1$
0&
#124
0$
1&
1'
#125
1$
0&
0'
#126
0$
#127
1$
1&
1'
#128
0$
0&
0'
#129
1$
1&
#130
0$
0&
1'
#131
1$
1&
0'
#132
0$
0&
#133
b01 #
1$
1'
b01 (
b11 )
#134
0$
1&
0'
#135
1$
0&
#136
0$
1&
1'
#137
1$
0&
0'
#138
0$
1&
#139
1$
0&
1'
#140
0$
0'
#141
b10 #
1$
1&
b10 (
b00 )
#142
0$
0&
1'
#143
1$
1&
0'
#144
0$
0&
#145
1$
1&
1'
#146
0$
0&
0'
#147
b11 #
1$
b11 (
b01 )
#148
0$
1&
1'
#149
1$
0&
0'
#150
0$
1&
#151
1$
0&
1'
#152
0$
1&
0'
#153
1$
0&
#154
0$
1'
#155
b00 #
1$
1&
0'
b00 (
b10 )
#156
0$
0&
#157
1$
1&
1'
#158
0$
0&
0'
#159
1$
1&
#160
0$
0&
1'
#161
1$
0'
#162
0$
1&
#163
1$
0&
1'
#164
0$
1&
0'
#165
1$
0&
#166
0$
1&
1'
#167
1$
0&
0'
#168
0$
#169
1$
1&
1'
#170
0$
0&
0'
#171
1$
1&
#172
0$
0&
1'
#173
1$
1&
0'
#174
0$
0&
#175
b01 #
1$
1'
b01 (
b11 )
#176
0$
1&
0'
#177
1$
0&
#178
0$
1&
1'
#179
1$
0&
0'
#180
0$
1&
#181
1$
0&
1'
#182
0$
0'
#183
b10 #
1$
1&
b10 (
b00 )
#184
0$
0&
1'
#185
1$
1&
0'
#186
0$
0&
#187
1$
1&
1'
#188
0$
0&
0'
#189
b11 #
1$
b11 (
b01 )
#190
0$
1&
1'
#191
1$
0&
0'
#192
0$
1&
#193
1$
0&
1'
#194
0$
1&
0'
#195
1$
0&
#196
0$
1'
#197
b00 #
1$
1&
0'
b00 (
b10 )
#198
0$
0&
#199
1$
1&
1'
#200
0$
0&
0'
#201
1$
1&
#202
0$
0&
1'
#203
1$
0'
#204
0$
1&
#205
1$
0&
1'
#206
0$
1&
0'
#207
1$
0&
#208
0$
1&
1'
#209
1$
0&
0'
#210
0$
#211
1$
1&
1'
#212
0$
0&
0'
#213
1$
1&
#214
0$
0&
1'
#215
1$
1&
0'
#216
0$
0&
#217
b01 #
1$
1'
b01 (
b11 )
#218
0$
1&
0'
#219
1$
0&
#220
0$
1&
1'
#221
1$
0&
0'
#222
0$
1&
#223
1$
0&
1'
#224
0$
0'
#225
b10 #
1$
1&
b10 (
b00 )
#226
0$
0&
1'
#227
1$
1&
0'
#228
0$
0&
#229
1$
1&
1'
#230
0$
0&
0'
#231
b11 #
1$
b11 (
b01 )
#232
0$
1&
1'
#233
1$
0&
0'
#234
0$
1&
#235
1$
0&
1'
#236
0$
1&
0'
#237
1$
0&
#238
0$
1'
#239
b00 #
1$
1&
0'
b00 (
b10 )
#240
0$
0&
#241
1$
1&
1'
#242
0$
0&
0'
#243
1$
1&
#244
0$
0&
1'
#245
1$
0'
#246
0$
1&
#247
1$
0&
1'
#248
0$
1&
0'
#249
1$
0&
#250
0$
1&
1'
#251
1$
0&
0'
#252
0$
#253
1$
1&
1'
#254
0$
0&
0'
#255
1$
1&
#256
0$
0&
1'
#257
1$
1&
0'
#258
0$
0&
#259
b01 #
1$
1'
b01 (
b11 )
#260
0$
1&
0'
#261
1$
0&
#262
0$
1&
1'
#263
1$
0&
0'
#264
0$
1&
#265
1$
0&
1'
#266
0$
0'
#267
b10 #
1$
1&
b10 (
b00 )
#268
0$
0&
1'
#269
1$
1&
0'
#270
0$
0&
#271
1$
1&
1'
#272
0$
0&
0'
#273
b11 #
1$
b11 (
b01 )
#274
0$
1&
1'
#275
1$
0&
0'
#276
0$
1&
#277
1$
0&
1'
#278
0$
1&
0'
#279
1$
0&
#280
0$
1'
#281
b00 #
1$
1&
0'
b00 (
b10 )
#282
0$
0&
#283
1$
1&
1'
#284
0$
0&
0'
#285
1$
1&
#286
0$
0&
1'
#287
1$
0'
#288
0$
1&
#289
1$
0&
1'
#290
0$
1&
0'
#291
1$
0&
#292
0$
1&
1'
#293
1$
0&
0'
#294
0$
#295
1$
1&
1'
#296
0$
0&
0'
#297
1$
1&
#298
0$
0&
1'
#299
1$
1&
0'
#300
0$
0&
#301
b01 #
1$
1'
b01 (
b11 )
#302
0$
1&
0'
#303
1$
0&
#304
0$
1&
1'
#305
1$
0&
0'
#306
0$
1&
#307
1$
0&
1'
#308
0$
0'
#309
b10 #
1$
1&
b10 (
b00 )
#310
0$
0&
1'
#311
1$
1&
0'
#312
0$
0&
#313
1$
1&
1'
#314
0$
0&
0'
#315
b11 #
1$
b11 (
b01 )
#316
0$
1&
1'
#317
1$
0&
0'
#318
0$
1&
#319
1$
0&
1'
#320
0$
1&
0'
#321
1$
0&
#322
0$
1'
#323
b00 #
1$
1&
0'
b00 (
b10 )
#324
0$
0&
#325
1$
1&
1'
#326
0$
0&
0'
#327
1$
1&
#328
0$
0&
1'
#329
1$
0'
#330
0$
1&
#331
1$
0&
1'
#332
0$
1&
0'
#333
1$
0&
#334
0$
1&
1'
#335
1$
0&
0'
#336
0$
#337
1$
1&
1'
#338
0$
0&
0'
#339
1$
1&
#340
0$
0&
1'
#341
1$
1&
0'
#342
0$
0&
#343
b01 #
1$
1'
b01 (
b11 )
#344
0$
1&
0'
#345
1$
0&
#346
0$
1&
1'
#347
1$
0&
0'
#348
0$
1&
#349
1$
0&
1'
#350
0$
0'
#351
b10 #
1$
1&
b10 (
b00 )
#352
0$
0&
1'
#353
1$
1&
0'
#354
0$
0&
#355
1$
1&
1'
#356
0$
0&
0'
#357
b11 #
1$
b11 (
b01 )
#358
0$
1&
1'
#359
1$
0&
0'
#360
0$
1&
#361
1$
0&
1'
#362
0$
1&
0'
#363
1$
0&
#364
0$
1'
#365
b00 #
1$
1&
0'
b00 (
b10 )
#366
0$
0&
#367
1$
1&
1'
#368
0$
0&
0'
#369
1$
1&
#370
0$
0&
1'
#371
1$
0'
#372
0$
1&
#373
1$
0&
1'
#374
0$
1&
0'
#375
1$
0&
#376
0$
1&
1'
#377
1$
0&
0'
#378
0$
#379
1$
1&
1'
#380
0$
0&
0'
#381
1$
1&
#382
0$
0&
1'
#383
1$
1&
0'
#384
0$
0&
#385
b01 #
1$
1'
b01 (
b11 )
#386
0$
1&
0'
#387
1$
0&
#388
0$
1&
1'
#389
1$
0&
0'
#390
0$
1&
#391
1$
0&
1'
#392
0$
0'
#393
b10 #
1$
1&
b10 (
b00 )
#394
0$
0&
1'
#395
1$
1&
0'
#396
0$
0&
#397
1$
1&
1'
#398
0$
0&
0'
#399
b11 #
1$
b11 (
b01 )
#400
0$
1&
1'
#401
1$
0&
0'
#402
0$
1&
#403
1$
0&
1'
#404
0$
1&
0'
#405
1$
0&
#406
0$
1'
#407
b00 #
1$
1&
0'
b00 (
b10 )
#408
0$
0&
#409
1$
1&
1'
#410
0$
0&
0'
#411
1$
1&
#412
0$
0&
1'
#413
1$
0'
#414
0$
1&
#415
1$
0&
1'
#416
0$
1&
0'
#417
1$
0&
#418
0$
1&
1'
#419
1$
0&
0'
#420
0$
#421
1$
1&
1'
#422
0$
0&
0'
#423
1$
1&
#424
0$
0&
1'
#425
1$
1&
0'
#426
0$
0&
#427
b01 #
1$
1'
b01 (
b11 )
#428
0$
1&
0'
#429
1$
0&
#430
0$
1&
1'
#431
1$
0&
0'
#432
0$
1&
#433
1$
0&
1'
#434
0$
0'
#435
b10 #
1$
1&
b10 (
b00 )
#436
0$
0&
1'
#437
1$
1&
0'
#438
0$
0&
#439
1$
1&
1'
#440
0$
0&
0'
#441
b11 #
1$
b11 (
b01 )
#442
0$
1&
1'
#443
1$
0&
0'
#444
0$
1&
#445
1$
0&
1'
#446
0$
1&
0'
#447
1$
0&
#448
0$
1'
#449
b00 #
1$
1&
0'
b00 (
b10 )
#450
0$
0&
#451
1$
1&
1'
#452
0$
0&
0'
#453
1$
1&
#454
0$
0&
1'
#455
1$
0'
#456
0$
1&
#457
1$
0&
1'
#458
0$
1&
0'
#459
1$
0&
#460
0$
1&
1'
#461
1$
0&
0'
#462
0$
#463
1$
1&
1'
#464
0$
0&
0'
#465
1$
1&
#466
0$
0&
1'
#467
1$
1&
0'
#468
0$
0&
#469
b01 #
1$
1'
b01 (
b11 )
#470
0$
1&
0'
#471
1$
0&
#472
0$
1&
1'
#473
1$
0&
0'
#474
0$
1&
#475
1$
0&
1'
#476
0$
0'
#477
b10 #
1$
1&
b10 (
b00 )
#478
0$
0&
1'
#479
1$
1&
0'
#480
0$
0&
#481
1$
1&
1'
#482
0$
0&
0'
#483
b11 #
1$
b11 (
b01 )
#484
0$
1&
1'
#485
1$
0&
0'
#486
0$
1&
#487
1$
0&
1'
#488
0$
1&
0'
#489
1$
0&
#490
0$
1'
#491
b00 #
1$
1&
0'
b00 (
b10 )
#492
0$
0&
#493
1$
1&
1'
#494
0$
0&
0'
#495
1$
1&
#496
0$
0&
1'
#497
1$
0'
#498
0$
1&
#499
1$
0&
1'
#500
0$
1&
0'
#501
1$
0&
#502
0$
1&
1'
#503
1$
0&
0'
#504
0$
#505
1$
1&
1'
#506
0$
0&
0'
#507
1$
1&
#508
0$
0&
1'
#509
1$
1&
0'
#510
0$
0&
#511
b01 #
1$
1'
b01 (
b11 )
#512
0$
1&
0'
#513
1$
0&
#514
0$
1&
1'
#515
1$
0&
0'
#516
0$
1&
#517
1$
0&
1'
#518
0$
0'
#519
b10 #
1$
1&
b10 (
b00 )
#520
0$
0&
1'
#521
1$
1&
0'
#522
0$
0&
#523
1$
1&
1'
#524
0$
0&
0'
#525
b11 #
1$
b11 (
b01 )
#526
0$
1&
1'
#527
1$
0&
0'
#528
0$
1&
#529
1$
0&
1'
#530
0$
1&
0'
#531
1$
0&
#532
0$
1'
#533
b00 #
1$
1&
0'
b00 (
b10 )
#534
0$
0&
#535
1$
1&
1'
#536
0$
0&
0'
#537
1$
1&
#538
0$
0&
1'
#539
1$
0'
#540
0$
1&
#541
1$
0&
1'
#542
0$
1&
0'
#543
1$
0&
#544
0$
1&
1'
#545
1$
0&
0'
#546
0$
#547
1$
1&
1'
#548
0$
0&
0'
#549
1$
1&
#550
0$
0&
1'
#551
1$
1&
0'
#552
0$
0&
#553
b01 #
1$
1'
b01 (
b11 )
#554
0$
1&
0'
#555
1$
0&
#556
0$
1&
1'
#557
1$
0&
0'
#558
0$
1&
#559
1$
0&
1'
#560
0$
0'
#561
b10 #
1$
1&
b10 (
b00 )
#562
0$
0&
1'
#563
1$
1&
0'
#564
0$
0&
#565
1$
1&
1'
#566
0$
0&
0'
#567
b11 #
1$
b11 (
b01 )
#568
0$
1&
1'
#569
1$
0&
0'
#570
0$
1&
#571
1$
0&
1'
#572
0$
1&
0'
#573
1$
0&
#574
0$
1'
#575
b00 #
1$
1&
0'
b00 (
b10 )
#576
0$
0&
#577
1$
1&
1'
#578
0$
0&
0'
#579
1$
1&
#580
0$
0&
1'
#581
1$
0'
#582
0$
1&
#583
1$
0&
1'
#584
0$
1&
0'
#585
1$
0&
#586
0$
1&
1'
#587
1$
0&
0'
#588
0$
#589
1$
1&
1'
#590
0$
0&
0'
#591
1$
1&
#592
0$
0&
1'
#593
1$
1&
0'
#594
0$
0&
#595
b01 #
1$
1'
b01 (
b11 )
#596
0$
1&
0'
#597
1$
0&
#598
0$
1&
1'
#599
1$
0&
0'
#600
0$
1&
#601
1$
0&
1'
#602
0$
0'
#603
b10 #
1$
1&
b10 (
b00 )
#604
0$
0&
1'
#605
1$
1&
0'
#606
0$
0&
#607
1$
1&
1'
#608
0$
0&
0'
#609
b11 #
1$
b11 (
b01 )
#610
0$
1&
1'
#611
1$
0&
0'
#612
0$
1&
#613
1$
0&
1'
#614
0$
1&
0'
#615
1$
0&
#616
0$
1'
#617
b00 #
1$
1&
0'
b00 (
b10 )
#618
0$
0&
#619
1$
1&
1'
#620
0$
0&
0'
#621
1$
1&
#622
0$
0&
1'
#623
1$
0'
#624
0$
1&
#625
1$
0&
1'
#626
0$
1&
0'
#627
1$
0&
#628
0$
1&
1'
#629
1$
0&
0'
#630
0$
#631
1$
1&
1'
#632
0$
0&
0'
#633
1$
1&
#634
0$
0&
1'
#635
1$
1&
0'
#636
0$
0&
#637
b01 #
1$
1'
b01 (
b11 )
#638
0$
1&
0'
#639
1$
0&
#640
0$
1&
1'
#641
1$
0&
0'
#642
0$
1&
#643
1$
0&
1'
#644
0$
0'
#645
b10 #
1$
1&
b10 (
b00 )
#646
0$
0&
1'
#647
1$
1&
0'
#648
0$
0&
#649
1$
1&
1'
#650
0$
0&
0'
#651
b11 #
1$
b11 (
b01 )
#652
0$
1&
1'
#653
1$
0&
0'
#654
0$
1&
#655
1$
0&
1'
#656
0$
1&
0'
#657
1$
0&
#658
0$
1'
#659
b00 #
1$
1&
0'
b00 (
b10 )
#660
0$
0&
#661
1$
1&
1'
#662
0$
0&
0'
#663
1$
1&
#664
0$
0&
1'
#665
1$
0'
#666
0$
1&
#667
1$
0&
1'
#668
0$
1&
0'
#669
1$
0&
#670
0$
1&
1'
#671
1$
0&
0'
#672
0$
#673
1$
1&
1'
#674
0$
0&
0'
#675
1$
1&
#676
0$
0&
1'
#677
1$
1&
0'
#678
0$
0&
#679
b01 #
1$
1'
b01 (
b11 )
#680
0$
1&
0'
#681
1$
0&
#682
0$
1&
1'
#683
1$
0&
0'
#684
0$
1&
#685
1$
0&
1'
#686
0$
0'
#687
b10 #
1$
1&
b10 (
b00 )
#688
0$
0&
1'
#689
1$
1&
0'
#690
0$
0&
#691
1$
1&
1'
#692
0$
0&
0'
#693
b11 #
1$
b11 (
b01 )
#694
0$
1&
1'
#695
1$
0&
0'
#696
0$
1&
#697
1$
0&
1'
#698
0$
1&
0'
#699
1$
0&
#700
0$
1'
#701
b00 #
1$
1&
0'
b00 (
b10 )
#702
0$
0&
#703
1$
1&
1'
#704
0$
0&
0'
#705
1$
1&
#706
0$
0&
1'
#707
1$
0'
#708
0$
1&
#709
1$
0&
1'
#710
0$
1&
0'
#711
1$
0&
#712
0$
1&
1'
#713
1$
0&
0'
#714
0$
#715
1$
1&
1'
#716
0$
0&
0'
#717
1$
1&
#718
0$
0&
1'
#719
1$
1&
0'
#720
0$
0&
#721
b01 #
1$
1'
b01 (
b11 )
#722
0$
1&
0'
#723
1$
0&
#724
0$
1&
1'
#725
1$
0&
0'
#726
0$
1&
#727
1$
0&
1'
#728
0$
0'
#729
b10 #
1$
1&
b10 (
b00 )
#730
0$
0&
1'
#731
1$
1&
0'
#732
0$
0&
#733
1$
1&
1'
#734
0$
0&
0'
#735
b11 #
1$
b11 (
b01 )
#736
0$
1&
1'
#737
1$
0&
0'
#738
0$
1&
#739
1$
0&
1'
#740
0$
1&
0'
#741
1$
0&
#742
0$
1'
#743
b00 #
1$
1&
0'
b00 (
b10 )
#744
0$
0&
#745
1$
1&
1'
#746
0$
0&
0'
#747
1$
1&
#748
0$
0&
1'
#749
1$
0'
#750
0$
1&
#751
1$
0&
1'
#752
0$
1&
0'
#753
1$
0&
#754
0$
1&
1'
#755
1$
0&
0'
#756
0$
#757
1$
1&
1'
#758
0$
0&
0'
#759
1$
1&
#760
0$
0&
1'
#761
1$
1&
0'
#762
0$
0&
#763
b01 #
1$
1'
b01 (
b11 )
#764
0$
1&
0'
#765
1$
0&
#766
0$
1&
1'
#767
1$
0&
0'
#768
0$
1&
#769
1$
0&
1'
#770
0$
0'
#771
b10 #
1$
1&
b10 (
b00 )
#772
0$
0&
1'
#773
1$
1&
0'
#774
0$
0&
#775
1$
1&
1'
#776
0$
0&
0'
#777
b11 #
1$
b11 (
b01 )
#778
0$
1&
1'
#779
1$
0&
0'
#780
0$
1&
#781
1$
0&
1'
#782
0$
1&
0'
#783
1$
0&
#784
0$
1'
#785
b00 #
1$
1&
0'
b00 (
b10 )
#786
0$
0&
#787
1$
1&
1'
#788
0$
0&
0'
#789
1$
1&
#790
0$
0&
1'
#791
1$
0'
#792
0$
1&
#793
1$
0&
1'
#794
0$
1&
0'
#795
1$
0&
#796
0$
1&
1'
#797
1$
0&
0'
#798
0$
#799
1$
1&
1'
#800
0$
0&
0'
#801
1$
1&
#802
0$
0&
1'
#803
1$
1&
0'
#804
0$
0&
#805
b01 #
1$
1'
b01 (
b11 )
#806
0$
1&
0'
#807
1$
0&
#808
0$
1&
1'
#809
1$
0&
0'
#810
0$
1&
#811
1$
0&
1'
#812
0$
0'
#813
b10 #
1$
1&
b10 (
b00 )
#814
0$
0&
1'
#815
1$
1&
0'
#816
0$
0&
#817
1$
1&
1'
#818
0$
0&
0'
#819
b11 #
1$
b11 (
b01 )
#820
0$
1&
1'
#821
1$
0&
0'
#822
0$
1&
#823
1$
0&
1'
#824
0$
1&
0'
#825
1$
0&
#826
0$
1'
#827
b00 #
1$
1&
0'
b00 (
b10 )
#828
0$
0&
#829
1$
1&
1'
#830
0$
0&
0'
#831
1$
1&
#832
0$
0&
1'
#833
1$
0'
#834
0$
1&
#835
1$
0&
1'
#836
0$
1&
0'
#837
1$
0&
#838
0$
1&
1'
#839
1$
0&
0'
#840
0$
#841
1$
1&
1'
#842
0$
0&
0'
#843
1$
1&
#844
0$
0&
1'
#845
1$
1&
0'
#846
0$
0&
#847
b01 #
1$
1'
b01 (
b11 )
#848
0$
1&
0'
#849
1$
0&
#850
0$
1&
1'
#851
1$
0&
0'
#852
0$
1&
#853
1$
0&
1'
#854
0$
0'
#855
b10 #
1$
1&
b10 (
b00 )
#856
0$
0&
1'
#857
1$
1&
0'
#858
0$
0&
#859
1$
1&
1'
#860
0$
0&
0'
#861
b11 #
1$
b11 (
b01 )
#862
0$
1&
1'
#863
1$
0&
0'
#864
0$
1&
#865
1$
0&
1'
#866
0$
1&
0'
#867
1$
0&
#868
0$
1'
#869
b00 #
1$
1&
0'
b00 (
b10 )
#870
0$
0&
#871
1$
1&
1'
#872
0$
0&
0'
#873
1$
1&
#874
0$
0&
1'
#875
1$
0'
#876
0$
1&
#877
1$
0&
1'
#878
0$
1&
0'
#879
1$
0&
#880
0$
1&
1'
#881
1$
0&
0'
#882
0$
#883
1$
1&
1'
#884
0$
0&
0'
#885
1$
1&
#886
0$
0&
1'
#887
1$
1&
0'
#888
0$
0&
#889
b01 #
1$
1'
b01 (
b11 )
#890
0$
1&
0'
#891
1$
0&
#892
0$
1&
1'
#893
1$
0&
0'
#894
0$
1&
#895
1$
0&
1'
#896
0$
0'
#897
b10 #
1$
1&
b10 (
b00 )
#898
0$
0&
1'
#899
1$
1&
0'
#900
0$
0&
#901
1$
1&
1'
#902
0$
0&
0'
#903
b11 #
1$
b11 (
b01 )
#904
0$
1&
1'
#905
1$
0&
0'
#906
0$
1&
#907
1$
0&
1'
#908
0$
1&
0'
#909
1$
0&
#910
0$
1'
#911
b00 #
1$
1&
0'
b00 (
b10 )
#912
0$
0&
#913
1$
1&
1'
#914
0$
0&
0'
#915
1$
1&
#916
0$
0&
1'
#917
1$
0'
#918
0$
1&
#919
1$
0&
1'
#920
0$
1&
0'
#921
1$
0&
#922
0$
1&
1'
#923
1$
0&
0'
#924
0$
#925
1$
1&
1'
#926
0$
0&
0'
#927
1$
1&
#928
0$
0&
1'
#929
1$
1&
0'
#930
0$
0&
#931
b01 #
1$
1'
b01 (
b11 )
#932
0$
1&
0'
#933
1$
0&
#934
0$
1&
1'
#935
1$
0&
0'
#936
0$
1&
#937
1$
0&
1'
#938
0$
0'
#939
b10 #
1$
1&
b10 (
b00 )
#940
0$
0&
1'
#941
1$
1&
0'
#942
0$
0&
#943
1$
1&
1'
#944
0$
0&
0'
#945
b11 #
1$
b11 (
b01 )
#946
0$
1&
1'
#947
1$
0&
0'
#948
0$
1&
#949
1$
0&
1'
#950
0$
1&
0'
#951
1$
0&
#952
0$
1'
#953
b00 #
1$
1&
0'
b00 (
b10 )
#954
0$
0&
#955
1$
1&
1'
#956
0$
0&
0'
#957
1$
1&
#958
0$
0&
1'
#959
1$
0'
#960
0$
1&
#961
1$
0&
1'
#962
0$
1&
0'
#963
1$
0&
#964
0$
1&
1'
#965
1$
0&
0'
#966
0$
#967
1$
1&
1'
#968
0$
0&
0'
#969
1$
1&
#970
0$
0&
1'
#971
1$
1&
0'
#972
0$
0&
#973
b01 #
1$
1'
b01 (
b11 )
#974
0$
1&
0'
#975
1$
0&
#976
0$
1&
1'
#977
1$
0&
0'
#978
0$
1&
#979
1$
0&
1'
#980
0$
0'
#981
b10 #
1$
1&
b10 (
b00 )
#982
0$
0&
1'
#983
1$
1&
0'
#984
0$
0&
#985
1$
1&
1'
#986
0$
0&
0'
#987
b11 #
1$
b11 (
b01 )
#988
0$
1&
1'
#989
1$
0&
0'
#990
0$
1&
#991
1$
0&
1'
#992
0$
1&
0'
#993
1$
0&
#994
0$
1'
#995
b00 #
1$
1&
0'
b00 (
b10 )
#996
0$
0&
#997
1$
1&
1'
#998
0$
0&
0'
#999
1$
1&
